mcp_clippy/__init__.py
mcp_clippy/app.py
mcp_clippy/config.py
mcp_clippy/console.py
mcp_clippy/context.py
mcp_clippy/context_dependent.py
mcp_clippy/event_progress.py
mcp_clippy/mcp_server_registry.py
mcp_clippy/progress_display.py
mcp_clippy/py.typed
mcp_clippy/agents/__init__.py
mcp_clippy/agents/agent.py
mcp_clippy/cli/__init__.py
mcp_clippy/cli/__main__.py
mcp_clippy/cli/main.py
mcp_clippy/cli/terminal.py
mcp_clippy/cli/commands/config.py
mcp_clippy/core/decorator_app.py
mcp_clippy/data/artificial_analysis_llm_benchmarks.json
mcp_clippy/eval/__init__.py
mcp_clippy/executor/__init__.py
mcp_clippy/executor/decorator_registry.py
mcp_clippy/executor/executor.py
mcp_clippy/executor/task_registry.py
mcp_clippy/executor/temporal.py
mcp_clippy/executor/workflow.py
mcp_clippy/executor/workflow_signal.py
mcp_clippy/human_input/__init__.py
mcp_clippy/human_input/handler.py
mcp_clippy/human_input/types.py
mcp_clippy/logging/__init__.py
mcp_clippy/logging/events.py
mcp_clippy/logging/json_serializer.py
mcp_clippy/logging/listeners.py
mcp_clippy/logging/logger.py
mcp_clippy/logging/rich_progress.py
mcp_clippy/logging/tracing.py
mcp_clippy/logging/transport.py
mcp_clippy/mcp/__init__.py
mcp_clippy/mcp/gen_client.py
mcp_clippy/mcp/mcp_activity.py
mcp_clippy/mcp/mcp_agent_client_session.py
mcp_clippy/mcp/mcp_agent_server.py
mcp_clippy/mcp/mcp_aggregator.py
mcp_clippy/mcp/mcp_connection_manager.py
mcp_clippy/mcp/stdio.py
mcp_clippy/telemetry/__init__.py
mcp_clippy/telemetry/usage_tracking.py
mcp_clippy/workflows/__init__.py
mcp_clippy/workflows/embedding/__init__.py
mcp_clippy/workflows/embedding/embedding_base.py
mcp_clippy/workflows/embedding/embedding_cohere.py
mcp_clippy/workflows/embedding/embedding_openai.py
mcp_clippy/workflows/evaluator_optimizer/__init__.py
mcp_clippy/workflows/evaluator_optimizer/evaluator_optimizer.py
mcp_clippy/workflows/intent_classifier/__init__.py
mcp_clippy/workflows/intent_classifier/intent_classifier_base.py
mcp_clippy-0.0.8.dist-info/METADATA
mcp_clippy-0.0.8.dist-info/WHEEL
mcp_clippy-0.0.8.dist-info/entry_points.txt
mcp_clippy-0.0.8.dist-info/licenses/LICENSE
mcp_clippy-0.0.8.dist-info/RECORD
