Metadata-Version: 2.4
Name: mcp-clippy
Version: 0.0.8
Summary: Build effective agents with Model Context Protocol (MCP) using simple, composable patterns.
Author-email: Sarmad Qadri <sarmad@lastmileai.dev>
License:                                  Apache License
License-File: LICENSE
Classifier: License :: OSI Approved :: Apache Software License
Classifier: Operating System :: OS Independent
Classifier: Programming Language :: Python :: 3
Requires-Python: >=3.10
Requires-Dist: fastapi>=0.115.6
Requires-Dist: instructor>=1.7.0
Requires-Dist: mcp>=1.2.1
Requires-Dist: numpy>=2.2.1
Requires-Dist: opentelemetry-distro>=0.50b0
Requires-Dist: opentelemetry-exporter-otlp-proto-http>=1.29.0
Requires-Dist: pydantic-settings>=2.7.0
Requires-Dist: pydantic>=2.10.4
Requires-Dist: pyyaml>=6.0.2
Requires-Dist: rich>=13.9.4
Requires-Dist: scikit-learn>=1.6.0
Requires-Dist: typer>=0.15.1
Provides-Extra: anthropic
Requires-Dist: anthropic>=0.42.0; extra == 'anthropic'
Requires-Dist: instructor[anthropic]>=1.7.2; extra == 'anthropic'
Provides-Extra: cohere
Requires-Dist: cohere>=5.13.4; extra == 'cohere'
Provides-Extra: openai
Requires-Dist: openai>=1.58.1; extra == 'openai'
Provides-Extra: temporal
Requires-Dist: temporalio>=1.8.0; extra == 'temporal'
